pycocowriter/__init__.py
pycocowriter/coco.py
pycocowriter/coco2csv.py
pycocowriter/coco2yolo.py
pycocowriter/cocomerge.py
pycocowriter/csv2coco.py
pycocowriter/utils.py
pycocowriter-0.4.1.dist-info/licenses/LICENSE
pycocowriter-0.4.1.dist-info/WHEEL
pycocowriter-0.4.1.dist-info/METADATA
pycocowriter-0.4.1.dist-info/RECORD
