Metadata-Version: 2.4
Name: pycocowriter
Version: 0.4.1
Summary: tools for writing coco files
Author: CScott Brown
Classifier: Programming Language :: Python :: 3
License-File: LICENSE
Requires-Dist: numpy
Requires-Dist: pycocotools
Requires-Dist: pillow
Requires-Dist: mkdocs ; extra == "dev"
Requires-Dist: mkdocs-material ; extra == "dev"
Requires-Dist: mkdocstrings[python] ; extra == "dev"
Project-URL: Documentation, https://nodd-tools.github.io/pycocowriter/
Project-URL: Source, https://github.com/nodd-tools/pycocowriter
Provides-Extra: dev
